{ "columns":8,
 "image":"tree.png",
 "imageheight":48,
 "imagewidth":64,
 "margin":0,
 "name":"arvore",
 "spacing":0,
 "tilecount":48,
 "tiledversion":"1.9.1",
 "tileheight":8,
 "tiles":[
        {
         "id":2,
         "objectgroup":
            {
             "draworder":"index",
             "id":2,
             "name":"",
             "objects":[
                    {
                     "class":"",
                     "height":3.01811362950429,
                     "id":1,
                     "name":"",
                     "rotation":0,
                     "visible":true,
                     "width":3.98292044549336,
                     "x":4.00765908180077,
                     "y":4.94772726148244
                    }],
             "opacity":1,
             "type":"objectgroup",
             "visible":true,
             "x":0,
             "y":0
            }
        }, 
        {
         "id":3,
         "objectgroup":
            {
             "draworder":"index",
             "id":2,
             "name":"",
             "objects":[
                    {
                     "class":"",
                     "height":4.00765908180077,
                     "id":1,
                     "name":"",
                     "rotation":0,
                     "visible":true,
                     "width":8.04005679990896,
                     "x":-0.0494772726148244,
                     "y":3.93344317287854
                    }],
             "opacity":1,
             "type":"objectgroup",
             "visible":true,
             "x":0,
             "y":0
            }
        }, 
        {
         "id":4,
         "objectgroup":
            {
             "draworder":"index",
             "id":2,
             "name":"",
             "objects":[
                    {
                     "class":"",
                     "height":4.13135226333783,
                     "id":1,
                     "name":"",
                     "rotation":0,
                     "visible":true,
                     "width":8.01531816360155,
                     "x":0.0247386363074122,
                     "y":3.76027271872665
                    }],
             "opacity":1,
             "type":"objectgroup",
             "visible":true,
             "x":0,
             "y":0
            }
        }, 
        {
         "id":5,
         "objectgroup":
            {
             "draworder":"index",
             "id":2,
             "name":"",
             "objects":[
                    {
                     "class":"",
                     "height":2.96863635688946,
                     "id":1,
                     "name":"",
                     "rotation":0,
                     "visible":true,
                     "width":4.10661362703042,
                     "x":-0.0494772726148245,
                     "y":4.99720453409726
                    }],
             "opacity":1,
             "type":"objectgroup",
             "visible":true,
             "x":0,
             "y":0
            }
        }, 
        {
         "id":10,
         "objectgroup":
            {
             "draworder":"index",
             "id":2,
             "name":"",
             "objects":[
                    {
                     "class":"",
                     "height":7.89162498206449,
                     "id":1,
                     "name":"",
                     "rotation":0,
                     "visible":true,
                     "width":7.9163636183719,
                     "x":0.0742159089222366,
                     "y":0.0742159089222366
                    }],
             "opacity":1,
             "type":"objectgroup",
             "visible":true,
             "x":0,
             "y":0
            }
        }, 
        {
         "id":14,
         "objectgroup":
            {
             "draworder":"index",
             "id":2,
             "name":"",
             "objects":[
                    {
                     "class":"",
                     "height":1.11323863383355,
                     "id":1,
                     "name":"",
                     "rotation":0,
                     "visible":true,
                     "width":1.2121931790632,
                     "x":-0.0742159089222366,
                     "y":6.87734089346059
                    }],
             "opacity":1,
             "type":"objectgroup",
             "visible":true,
             "x":0,
             "y":0
            }
        }, 
        {
         "id":17,
         "objectgroup":
            {
             "draworder":"index",
             "id":2,
             "name":"",
             "objects":[
                    {
                     "class":"",
                     "height":7.94110225467931,
                     "id":1,
                     "name":"",
                     "rotation":0,
                     "visible":true,
                     "width":3.36445453780806,
                     "x":4.57664771687125,
                     "y":0.0742159089222366
                    }],
             "opacity":1,
             "type":"objectgroup",
             "visible":true,
             "x":0,
             "y":0
            }
        }, 
        {
         "id":22,
         "objectgroup":
            {
             "draworder":"index",
             "id":2,
             "name":"",
             "objects":[
                    {
                     "class":"",
                     "height":7.9163636183719,
                     "id":1,
                     "name":"",
                     "rotation":0,
                     "visible":true,
                     "width":5.24459089717138,
                     "x":-0.0247386363074122,
                     "y":0
                    }],
             "opacity":1,
             "type":"objectgroup",
             "visible":true,
             "x":0,
             "y":0
            }
        }, 
        {
         "id":25,
         "objectgroup":
            {
             "draworder":"index",
             "id":2,
             "name":"",
             "objects":[
                    {
                     "class":"",
                     "height":7.89162498206449,
                     "id":1,
                     "name":"",
                     "rotation":0,
                     "visible":true,
                     "width":4.94772726148244,
                     "x":3.01811362950429,
                     "y":0.0742159089222366
                    }],
             "opacity":1,
             "type":"objectgroup",
             "visible":true,
             "x":0,
             "y":0
            }
        }, 
        {
         "id":30,
         "objectgroup":
            {
             "draworder":"index",
             "id":2,
             "name":"",
             "objects":[
                    {
                     "class":"",
                     "height":7.96584089098672,
                     "id":1,
                     "name":"",
                     "rotation":0,
                     "visible":true,
                     "width":5.21985226086397,
                     "x":0.0247386363074122,
                     "y":-0.0247386363074122
                    }],
             "opacity":1,
             "type":"objectgroup",
             "visible":true,
             "x":0,
             "y":0
            }
        }, 
        {
         "id":33,
         "objectgroup":
            {
             "draworder":"index",
             "id":2,
             "name":"",
             "objects":[
                    {
                     "class":"",
                     "height":4.08187499072301,
                     "id":1,
                     "name":"",
                     "rotation":0,
                     "visible":true,
                     "width":3.01811362950429,
                     "x":4.97246589778985,
                     "y":0.0494772726148244
                    }],
             "opacity":1,
             "type":"objectgroup",
             "visible":true,
             "x":0,
             "y":0
            }
        }, 
        {
         "id":34,
         "objectgroup":
            {
             "draworder":"index",
             "id":2,
             "name":"",
             "objects":[
                    {
                     "class":"",
                     "height":7.94110225467931,
                     "id":1,
                     "name":"",
                     "rotation":0,
                     "visible":true,
                     "width":7.94110225467931,
                     "x":0.0247386363074122,
                     "y":0.0247386363074122
                    }],
             "opacity":1,
             "type":"objectgroup",
             "visible":true,
             "x":0,
             "y":0
            }
        }, 
        {
         "id":35,
         "objectgroup":
            {
             "draworder":"index",
             "id":2,
             "name":"",
             "objects":[
                    {
                     "class":"",
                     "height":7.86688634575708,
                     "id":1,
                     "name":"",
                     "rotation":0,
                     "visible":true,
                     "width":7.81740907314225,
                     "x":0.0742159089222366,
                     "y":0.0247386363074122
                    }],
             "opacity":1,
             "type":"objectgroup",
             "visible":true,
             "x":0,
             "y":0
            }
        }, 
        {
         "id":36,
         "objectgroup":
            {
             "draworder":"index",
             "id":2,
             "name":"",
             "objects":[
                    {
                     "class":"",
                     "height":7.84214770944966,
                     "id":1,
                     "name":"",
                     "rotation":0,
                     "visible":true,
                     "width":7.96584089098672,
                     "x":0.0494772726148244,
                     "y":0.0742159089222366
                    }],
             "opacity":1,
             "type":"objectgroup",
             "visible":true,
             "x":0,
             "y":0
            }
        }, 
        {
         "id":37,
         "objectgroup":
            {
             "draworder":"index",
             "id":2,
             "name":"",
             "objects":[
                    {
                     "class":"",
                     "height":7.86688634575708,
                     "id":1,
                     "name":"",
                     "rotation":0,
                     "visible":true,
                     "width":7.94110225467931,
                     "x":0.0247386363074122,
                     "y":0.123693181537061
                    }],
             "opacity":1,
             "type":"objectgroup",
             "visible":true,
             "x":0,
             "y":0
            }
        }, 
        {
         "id":38,
         "objectgroup":
            {
             "draworder":"index",
             "id":3,
             "name":"",
             "objects":[
                    {
                     "class":"",
                     "height":3.95818180918595,
                     "id":2,
                     "name":"",
                     "rotation":0,
                     "visible":true,
                     "width":3.38919317411547,
                     "x":0.0494772726148244,
                     "y":0.098954545229649
                    }],
             "opacity":1,
             "type":"objectgroup",
             "visible":true,
             "x":0,
             "y":0
            }
        }],
 "tilewidth":8,
 "type":"tileset",
 "version":"1.8"
}